odoo10_addon_crm_lead_project-10.0.1.0.0.99.dev8-py3.8-nspkg.pth
odoo/addons/crm_lead_project/README.rst
odoo/addons/crm_lead_project/__init__.py
odoo/addons/crm_lead_project/__manifest__.py
odoo/addons/crm_lead_project/i18n/crm_lead_project.pot
odoo/addons/crm_lead_project/models/__init__.py
odoo/addons/crm_lead_project/models/crm_lead.py
odoo/addons/crm_lead_project/models/project.py
odoo/addons/crm_lead_project/readme/CONTRIBUTORS.rst
odoo/addons/crm_lead_project/readme/DESCRIPTION.rst
odoo/addons/crm_lead_project/static/description/icon.png
odoo/addons/crm_lead_project/static/description/index.html
odoo/addons/crm_lead_project/tests/__init__.py
odoo/addons/crm_lead_project/tests/test_create_project.py
odoo/addons/crm_lead_project/views/crm_lead.xml
odoo/addons/crm_lead_project/views/crm_project.xml
odoo/addons/crm_lead_project/views/project.xml
odoo/addons/crm_lead_project/wizard/__init__.py
odoo/addons/crm_lead_project/wizard/crm_lead_to_opportunity.py
odoo/addons/crm_lead_project/wizard/crm_lead_to_opportunity.xml
odoo/addons/crm_lead_project/wizard/crm_opportunity_create_project.py
odoo/addons/crm_lead_project/wizard/crm_opportunity_create_project.xml
odoo10_addon_crm_lead_project-10.0.1.0.0.99.dev8.dist-info/METADATA
odoo10_addon_crm_lead_project-10.0.1.0.0.99.dev8.dist-info/WHEEL
odoo10_addon_crm_lead_project-10.0.1.0.0.99.dev8.dist-info/namespace_packages.txt
odoo10_addon_crm_lead_project-10.0.1.0.0.99.dev8.dist-info/top_level.txt
odoo10_addon_crm_lead_project-10.0.1.0.0.99.dev8.dist-info/RECORD
